[{"time":0.0,"pose":{"rotation":{"radians":0.0},"translation":{"x":1.7297203685316462,"y":4.445378345302146}},"velocity":0,"acceleration":3.0,"curvature":0,"holonomicRotation":180.0,"angularVelocity":0.0,"holonomicAngularVelocity":0.0},{"time":0.08910839263388874,"pose":{"rotation":{"radians":0.0},"translation":{"x":1.7416308269883392,"y":4.445378345302146}},"velocity":0.26732517790166627,"acceleration":3.0000000000000004,"curvature":0,"holonomicRotation":180.0,"angularVelocity":0.0,"holonomicAngularVelocity":0.0},{"time":0.12554625041616038,"pose":{"rotation":{"radians":0.0},"translation":{"x":1.7533631600219821,"y":4.445378345302146}},"velocity":0.3766387512484812,"acceleration":2.9999999999999996,"curvature":0,"holonomicRotation":180.0,"angularVelocity":0.0,"holonomicAngularVelocity":0.0},{"time":0.15318493310652784,"pose":{"rotation":{"radians":0.0},"translation":{"x":1.7649188041279233,"y":4.445378345302146}},"velocity":0.4595547993195835,"acceleration":2.999999999999998,"curvature":0,"holonomicRotation":180.0,"angularVelocity":0.0,"holonomicAngularVelocity":0.0},{"time":0.17621734169270115,"pose":{"rotation":{"radians":0.0},"translation":{"x":1.7762991958015095,"y":4.445378345302146}},"velocity":0.5286520250781035,"acceleration":3.0000000000000036,"curvature":0,"holonomicRotation":180.0,"angularVelocity":0.0,"holonomicAngularVelocity":0.0},{"time":0.1962743029647395,"pose":{"rotation":{"radians":0.0},"translation":{"x":1.7875057715380878,"y":4.445378345302146}},"velocity":0.5888229088942185,"acceleration":2.9999999999999987,"curvature":0,"holonomicRotation":180.0,"angularVelocity":0.0,"holonomicAngularVelocity":0.0},{"time":0.2141955481973718,"pose":{"rotation":{"radians":0.0},"translation":{"x":1.7985399678330052,"y":4.445378345302146}},"velocity":0.6425866445921155,"acceleration":3.0000000000000013,"curvature":0,"holonomicRotation":180.0,"angularVelocity":0.0,"holonomicAngularVelocity":0.0},{"time":0.23048189032251984,"pose":{"rotation":{"radians":0.0},"translation":{"x":1.8094032211816093,"y":4.445378345302146}},"velocity":0.6914456709675596,"acceleration":3.0000000000000018,"curvature":0,"holonomicRotation":180.0,"angularVelocity":0.0,"holonomicAngularVelocity":-1.897432476726588e-12},{"time":0.24546092635095157,"pose":{"rotation":{"radians":0.0},"translation":{"x":1.8200969680792471,"y":4.445378345302146}},"velocity":0.7363827790528548,"acceleration":2.9999999999999982,"curvature":0,"holonomicRotation":179.99999999999997,"angularVelocity":0.0,"holonomicAngularVelocity":2.044700581138408e-12},{"time":0.2593611079680468,"pose":{"rotation":{"radians":0.0},"translation":{"x":1.8306226450212655,"y":4.445378345302146}},"velocity":0.7780833239041404,"acceleration":2.999999999999996,"curvature":0,"holonomicRotation":180.0,"angularVelocity":0.0,"holonomicAngularVelocity":0.0},{"time":0.2723494323736398,"pose":{"rotation":{"radians":0.0},"translation":{"x":1.840981688503012,"y":4.445378345302146}},"velocity":0.8170482971209193,"acceleration":2.9999999999999956,"curvature":0,"holonomicRotation":180.0,"angularVelocity":0.0,"holonomicAngularVelocity":0.0},{"time":0.2845524749358629,"pose":{"rotation":{"radians":0.0},"translation":{"x":1.8511755350198336,"y":4.445378345302146}},"velocity":0.8536574248075887,"acceleration":3.0000000000000044,"curvature":0,"holonomicRotation":180.0,"angularVelocity":0.0,"holonomicAngularVelocity":0.0},{"time":0.29606897004519234,"pose":{"rotation":{"radians":0.0},"translation":{"x":1.8612056210670778,"y":4.445378345302146}},"velocity":0.8882069101355771,"acceleration":3.000000000000005,"curvature":0,"holonomicRotation":180.0,"angularVelocity":0.0,"holonomicAngularVelocity":0.0},{"time":0.3069777566409277,"pose":{"rotation":{"radians":0.0},"translation":{"x":1.8710733831400912,"y":4.445378345302146}},"velocity":0.9209332699227831,"acceleration":3.0,"curvature":0,"holonomicRotation":180.0,"angularVelocity":0.0,"holonomicAngularVelocity":-2.7420149843602405e-12},{"time":0.31734302072318626,"pose":{"rotation":{"radians":0.0},"translation":{"x":1.8807802577342212,"y":4.445378345302146}},"velocity":0.9520290621695588,"acceleration":3.0,"curvature":0,"holonomicRotation":179.99999999999997,"angularVelocity":0.0,"holonomicAngularVelocity":2.878188412307389e-12},{"time":0.3272178813504024,"pose":{"rotation":{"radians":0.0},"translation":{"x":1.8903276813448153,"y":4.445378345302146}},"velocity":0.9816536440512074,"acceleration":3.0000000000000058,"curvature":0,"holonomicRotation":180.0,"angularVelocity":0.0,"holonomicAngularVelocity":0.0},{"time":0.3366469188289852,"pose":{"rotation":{"radians":0.0},"translation":{"x":1.8997170904672203,"y":4.445378345302146}},"velocity":1.0099407564869556,"acceleration":2.9999999999999942,"curvature":0,"holonomicRotation":180.0,"angularVelocity":0.0,"holonomicAngularVelocity":0.0},{"time":0.34566800359606836,"pose":{"rotation":{"radians":0.0},"translation":{"x":1.9089499215967836,"y":4.445378345302146}},"velocity":1.0370040107882053,"acceleration":3.0000000000000124,"curvature":0,"holonomicRotation":180.0,"angularVelocity":0.0,"holonomicAngularVelocity":0.0},{"time":0.35431364890184125,"pose":{"rotation":{"radians":0.0},"translation":{"x":1.9180276112288521,"y":4.445378345302146}},"velocity":1.062940946705524,"acceleration":3.000000000000006,"curvature":0,"holonomicRotation":180.0,"angularVelocity":0.0,"holonomicAngularVelocity":3.4249700436807385e-12},{"time":0.36261203080531035,"pose":{"rotation":{"radians":0.0},"translation":{"x":1.9269515958587733,"y":4.445378345302146}},"velocity":1.0878360924159314,"acceleration":3.0000000000000133,"curvature":0,"holonomicRotation":180.00000000000003,"angularVelocity":0.0,"holonomicAngularVelocity":-3.5635201962007423e-12},{"time":0.37058777048561464,"pose":{"rotation":{"radians":0.0},"translation":{"x":1.9357233119818942,"y":4.445378345302146}},"velocity":1.1117633114568444,"acceleration":3.0000000000000138,"curvature":0,"holonomicRotation":180.0,"angularVelocity":0.0,"holonomicAngularVelocity":0.0},{"time":0.37826254335837134,"pose":{"rotation":{"radians":0.0},"translation":{"x":1.944344196093562,"y":4.445378345302146}},"velocity":1.1347876300751143,"acceleration":2.9999999999999782,"curvature":0,"holonomicRotation":180.0,"angularVelocity":0.0,"holonomicAngularVelocity":0.0},{"time":0.3856555597572161,"pose":{"rotation":{"radians":0.0},"translation":{"x":1.9528156846891238,"y":4.445378345302146}},"velocity":1.1569666792716486,"acceleration":3.0000000000000075,"curvature":0,"holonomicRotation":180.0,"angularVelocity":0.0,"holonomicAngularVelocity":0.0},{"time":0.3927839488678057,"pose":{"rotation":{"radians":0.0},"translation":{"x":1.9611392142639268,"y":4.445378345302146}},"velocity":1.1783518466034175,"acceleration":3.000000000000008,"curvature":0,"holonomicRotation":180.0,"angularVelocity":0.0,"holonomicAngularVelocity":-4.131590948428627e-12},{"time":0.39966306874805757,"pose":{"rotation":{"radians":0.0},"translation":{"x":1.9693162213133182,"y":4.445378345302146}},"velocity":1.1989892062441732,"acceleration":3.000000000000008,"curvature":0,"holonomicRotation":179.99999999999997,"angularVelocity":0.0,"holonomicAngularVelocity":4.2780002822194235e-12},{"time":0.4063067591537204,"pose":{"rotation":{"radians":0.0},"translation":{"x":1.9773481423326453,"y":4.445378345302146}},"velocity":1.2189202774611616,"acceleration":3.0,"curvature":0,"holonomicRotation":180.0,"angularVelocity":0.0,"holonomicAngularVelocity":4.4265125475315405e-12},{"time":0.4127275495898061,"pose":{"rotation":{"radians":0.0},"translation":{"x":1.9852364138172551,"y":4.445378345302146}},"velocity":1.2381826487694187,"acceleration":2.9999999999999916,"curvature":0,"holonomicRotation":180.00000000000003,"angularVelocity":0.0,"holonomicAngularVelocity":0.0},{"time":0.4189368319375833,"pose":{"rotation":{"radians":0.0},"translation":{"x":1.9929824722624947,"y":4.445378345302146}},"velocity":1.2568104958127504,"acceleration":3.0000000000000178,"curvature":0,"holonomicRotation":180.00000000000003,"angularVelocity":0.0,"holonomicAngularVelocity":-9.461015910389147e-12},{"time":0.42494500478066966,"pose":{"rotation":{"radians":0.0},"translation":{"x":2.0005877541637114,"y":4.445378345302146}},"velocity":1.2748350143420095,"acceleration":3.0000000000000093,"curvature":0,"holonomicRotation":179.99999999999997,"angularVelocity":0.0,"holonomicAngularVelocity":4.886318058994872e-12},{"time":0.4307615949181218,"pose":{"rotation":{"radians":0.0},"translation":{"x":2.0080536960162525,"y":4.445378345302146}},"velocity":1.2922847847543661,"acceleration":3.000000000000019,"curvature":0,"holonomicRotation":180.0,"angularVelocity":0.0,"holonomicAngularVelocity":0.0},{"time":0.43639536033572357,"pose":{"rotation":{"radians":0.0},"translation":{"x":2.0153817343154654,"y":4.445378345302146}},"velocity":1.3091860810071714,"acceleration":3.0,"curvature":0,"holonomicRotation":180.0,"angularVelocity":0.0,"holonomicAngularVelocity":0.0},{"time":0.4418543779912487,"pose":{"rotation":{"radians":0.0},"translation":{"x":2.0225733055566963,"y":4.445378345302146}},"velocity":1.3255631339737468,"acceleration":3.0,"curvature":0,"holonomicRotation":180.0,"angularVelocity":0.0,"holonomicAngularVelocity":0.0},{"time":0.4471461190734314,"pose":{"rotation":{"radians":0.0},"translation":{"x":2.0296298462352933,"y":4.445378345302146}},"velocity":1.3414383572202948,"acceleration":3.0,"curvature":0,"holonomicRotation":180.0,"angularVelocity":0.0,"holonomicAngularVelocity":0.0},{"time":0.45227751385991366,"pose":{"rotation":{"radians":0.0},"translation":{"x":2.036552792846603,"y":4.445378345302146}},"velocity":1.3568325415797415,"acceleration":2.9999999999999782,"curvature":0,"holonomicRotation":180.0,"angularVelocity":0.0,"holonomicAngularVelocity":0.0},{"time":0.4572550078853352,"pose":{"rotation":{"radians":0.0},"translation":{"x":2.0433435818859733,"y":4.445378345302146}},"velocity":1.3717650236560062,"acceleration":3.000000000000011,"curvature":0,"holonomicRotation":180.0,"angularVelocity":0.0,"holonomicAngularVelocity":0.0},{"time":0.462084610807086,"pose":{"rotation":{"radians":0.0},"translation":{"x":2.0500036498487506,"y":4.445378345302146}},"velocity":1.3862538324212585,"acceleration":2.999999999999977,"curvature":0,"holonomicRotation":180.0,"angularVelocity":0.0,"holonomicAngularVelocity":0.0},{"time":0.4667719391013386,"pose":{"rotation":{"radians":0.0},"translation":{"x":2.056534433230282,"y":4.445378345302146}},"velocity":1.4003158173040162,"acceleration":3.0,"curvature":0,"holonomicRotation":180.0,"angularVelocity":0.0,"holonomicAngularVelocity":0.0},{"time":0.4713222535196554,"pose":{"rotation":{"radians":0.0},"translation":{"x":2.062937368525916,"y":4.445378345302146}},"velocity":1.4139667605589665,"acceleration":2.9999999999999636,"curvature":0,"holonomicRotation":180.0,"angularVelocity":0.0,"holonomicAngularVelocity":0.0},{"time":0.47574049207479463,"pose":{"rotation":{"radians":0.0},"translation":{"x":2.069213892230998,"y":4.445378345302146}},"velocity":1.4272214762243842,"acceleration":3.0,"curvature":0,"holonomicRotation":180.0,"angularVelocity":0.0,"holonomicAngularVelocity":0.0},{"time":0.4800312991942849,"pose":{"rotation":{"radians":0.0},"translation":{"x":2.075365440840876,"y":4.445378345302146}},"velocity":1.440093897582855,"acceleration":3.0,"curvature":0,"holonomicRotation":180.0,"angularVelocity":0.0,"holonomicAngularVelocity":0.0},{"time":0.48419905157503906,"pose":{"rotation":{"radians":0.0},"translation":{"x":2.0813934508508973,"y":4.445378345302146}},"velocity":1.4525971547251175,"acceleration":3.0,"curvature":0,"holonomicRotation":180.0,"angularVelocity":0.0,"holonomicAngularVelocity":0.0},{"time":0.4882478811865703,"pose":{"rotation":{"radians":0.0},"translation":{"x":2.0872993587564093,"y":4.445378345302146}},"velocity":1.4647436435597112,"acceleration":2.9999999999999862,"curvature":0,"holonomicRotation":180.0,"angularVelocity":0.0,"holonomicAngularVelocity":0.0},{"time":0.49218169580018045,"pose":{"rotation":{"radians":0.0},"translation":{"x":2.0930846010527584,"y":4.445378345302146}},"velocity":1.4765450874005417,"acceleration":3.000000000000014,"curvature":0,"holonomicRotation":180.0,"angularVelocity":0.0,"holonomicAngularVelocity":0.0},{"time":0.49600419736372253,"pose":{"rotation":{"radians":0.0},"translation":{"x":2.0987506142352923,"y":4.445378345302146}},"velocity":1.488012592091168,"acceleration":3.0000000000000147,"curvature":0,"holonomicRotation":180.0,"angularVelocity":0.0,"holonomicAngularVelocity":0.0},{"time":0.4997188984937513,"pose":{"rotation":{"radians":0.0},"translation":{"x":2.1042988347993585,"y":4.445378345302146}},"velocity":1.4991566954812543,"acceleration":3.000000000000015,"curvature":0,"holonomicRotation":180.0,"angularVelocity":0.0,"holonomicAngularVelocity":0.0},{"time":0.5033291373171614,"pose":{"rotation":{"radians":0.0},"translation":{"x":2.1097306992403033,"y":4.445378345302146}},"velocity":1.5099874119514847,"acceleration":2.9999999999999694,"curvature":0,"holonomicRotation":180.0,"angularVelocity":0.0,"holonomicAngularVelocity":0.0},{"time":0.5068380908612584,"pose":{"rotation":{"radians":0.0},"translation":{"x":2.1150476440534742,"y":4.445378345302146}},"velocity":1.5205142725837755,"acceleration":2.9999999999999685,"curvature":0,"holonomicRotation":180.0,"angularVelocity":0.0,"holonomicAngularVelocity":0.0},{"time":0.5102487871633942,"pose":{"rotation":{"radians":0.0},"translation":{"x":2.1202511057342184,"y":4.445378345302146}},"velocity":1.5307463614901826,"acceleration":2.9999999999999676,"curvature":0,"holonomicRotation":180.0,"angularVelocity":0.0,"holonomicAngularVelocity":-8.572816968062917e-12},{"time":0.5135641162479047,"pose":{"rotation":{"radians":0.0},"translation":{"x":2.1253425207778833,"y":4.445378345302146}},"velocity":1.540692348743714,"acceleration":3.0,"curvature":0,"holonomicRotation":179.99999999999997,"angularVelocity":0.0,"holonomicAngularVelocity":1.7638315133310776e-11},{"time":0.5167868400982942,"pose":{"rotation":{"radians":0.0},"translation":{"x":2.130323325679816,"y":4.445378345302146}},"velocity":1.5503605202948827,"acceleration":2.9999999999999654,"curvature":0,"holonomicRotation":180.00000000000003,"angularVelocity":0.0,"holonomicAngularVelocity":-9.072413646112517e-12},{"time":0.5199196017358307,"pose":{"rotation":{"radians":0.0},"translation":{"x":2.1351949569353637,"y":4.445378345302146}},"velocity":1.5597588052074924,"acceleration":3.000000000000071,"curvature":0,"holonomicRotation":180.0,"angularVelocity":0.0,"holonomicAngularVelocity":0.0},{"time":0.5229649335014264,"pose":{"rotation":{"radians":0.0},"translation":{"x":2.1399588510398733,"y":4.445378345302146}},"velocity":1.5688948005042793,"acceleration":3.0,"curvature":0,"holonomicRotation":180.0,"angularVelocity":0.0,"holonomicAngularVelocity":-9.600854850197578e-12},{"time":0.5259252646254636,"pose":{"rotation":{"radians":0.0},"translation":{"x":2.144616444488692,"y":4.445378345302146}},"velocity":1.577775793876391,"acceleration":2.9999999999999627,"curvature":0,"holonomicRotation":179.99999999999997,"angularVelocity":0.0,"holonomicAngularVelocity":9.876661774931553e-12},{"time":0.5288029281597706,"pose":{"rotation":{"radians":0.0},"translation":{"x":2.1491691737771674,"y":4.445378345302146}},"velocity":1.5864087844793118,"acceleration":2.9999999999999614,"curvature":0,"holonomicRotation":180.0,"angularVelocity":0.0,"holonomicAngularVelocity":0.0},{"time":0.5316001673369438,"pose":{"rotation":{"radians":0.0},"translation":{"x":2.153618475400646,"y":4.445378345302146}},"velocity":1.5948005020108316,"acceleration":3.0000000000000395,"curvature":0,"holonomicRotation":180.0,"angularVelocity":0.0,"holonomicAngularVelocity":-1.0453100551941123e-11},{"time":0.5343191414144606,"pose":{"rotation":{"radians":0.0},"translation":{"x":2.1579657858544756,"y":4.445378345302146}},"velocity":1.6029574242433817,"acceleration":2.999999999999959,"curvature":0,"holonomicRotation":179.99999999999997,"angularVelocity":0.0,"holonomicAngularVelocity":1.0754435011348386e-11},{"time":0.536961931054308,"pose":{"rotation":{"radians":0.0},"translation":{"x":2.1622125416340032,"y":4.445378345302146}},"velocity":1.610885793162924,"acceleration":2.999999999999958,"curvature":0,"holonomicRotation":180.0,"angularVelocity":0.0,"holonomicAngularVelocity":0.0},{"time":0.5395305432830348,"pose":{"rotation":{"radians":0.0},"translation":{"x":2.166360179234576,"y":4.445378345302146}},"velocity":1.6185916298491043,"acceleration":2.999999999999957,"curvature":0,"holonomicRotation":180.0,"angularVelocity":0.0,"holonomicAngularVelocity":0.0},{"time":0.542026916072068,"pose":{"rotation":{"radians":0.0},"translation":{"x":2.170410135151541,"y":4.445378345302146}},"velocity":1.6260807482162039,"acceleration":3.0000000000000444,"curvature":0,"holonomicRotation":180.0,"angularVelocity":0.0,"holonomicAngularVelocity":0.0},{"time":0.544452922573721,"pose":{"rotation":{"radians":0.0},"translation":{"x":2.1743638458802454,"y":4.445378345302146}},"velocity":1.633358767721163,"acceleration":3.0,"curvature":0,"holonomicRotation":180.0,"angularVelocity":0.0,"holonomicAngularVelocity":0.0},{"time":0.5468103750444573,"pose":{"rotation":{"radians":0.0},"translation":{"x":2.178222747916036,"y":4.445378345302146}},"velocity":1.6404311251333716,"acceleration":2.999999999999953,"curvature":0,"holonomicRotation":180.0,"angularVelocity":0.0,"holonomicAngularVelocity":0.0},{"time":0.5491010284835961,"pose":{"rotation":{"radians":0.0},"translation":{"x":2.1819882777542605,"y":4.445378345302146}},"velocity":1.647303085450788,"acceleration":2.9999999999999516,"curvature":0,"holonomicRotation":180.0,"angularVelocity":0.0,"holonomicAngularVelocity":0.0},{"time":0.5513265840126704,"pose":{"rotation":{"radians":0.0},"translation":{"x":2.1856618718902663,"y":4.445378345302146}},"velocity":1.653979752038011,"acceleration":3.0000000000000497,"curvature":0,"holonomicRotation":180.0,"angularVelocity":0.0,"holonomicAngularVelocity":0.0},{"time":0.553488692018036,"pose":{"rotation":{"radians":0.0},"translation":{"x":2.1892449668194005,"y":4.445378345302146}},"velocity":1.660466076054108,"acceleration":3.0000000000001026,"curvature":0,"holonomicRotation":180.0,"angularVelocity":0.0,"holonomicAngularVelocity":0.0},{"time":0.5555889550770206,"pose":{"rotation":{"radians":0.0},"translation":{"x":2.1927389990370094,"y":4.445378345302146}},"velocity":1.6667668652310617,"acceleration":3.0,"curvature":0,"holonomicRotation":180.0,"angularVelocity":0.0,"holonomicAngularVelocity":0.0},{"time":0.5576289306858668,"pose":{"rotation":{"radians":0.0},"translation":{"x":2.196145405038441,"y":4.445378345302146}},"velocity":1.6728867920576005,"acceleration":3.0,"curvature":0,"holonomicRotation":180.0,"angularVelocity":0.0,"holonomicAngularVelocity":0.0},{"time":0.5596101338059062,"pose":{"rotation":{"radians":0.0},"translation":{"x":2.1994656213190424,"y":4.445378345302146}},"velocity":1.6788304014177187,"acceleration":3.000000000000056,"curvature":0,"holonomicRotation":180.0,"angularVelocity":0.0,"holonomicAngularVelocity":0.0},{"time":0.5615340392428074,"pose":{"rotation":{"radians":0.0},"translation":{"x":2.2027010843741603,"y":4.445378345302146}},"velocity":1.6846021177284225,"acceleration":3.0000000000000577,"curvature":0,"holonomicRotation":180.0,"angularVelocity":0.0,"holonomicAngularVelocity":0.0},{"time":0.5634020838723124,"pose":{"rotation":{"radians":0.0},"translation":{"x":2.2058532306991423,"y":4.445378345302146}},"velocity":1.6902062516169374,"acceleration":3.0,"curvature":0,"holonomicRotation":180.0,"angularVelocity":0.0,"holonomicAngularVelocity":-1.5671563089316274e-11},{"time":0.5652156687245968,"pose":{"rotation":{"radians":0.0},"translation":{"x":2.208923496789336,"y":4.445378345302146}},"velocity":1.6956470061737907,"acceleration":3.0,"curvature":0,"holonomicRotation":179.99999999999997,"angularVelocity":0.0,"holonomicAngularVelocity":1.614418354692641e-11},{"time":0.5669761609382656,"pose":{"rotation":{"radians":0.0},"translation":{"x":2.2119133191400873,"y":4.445378345302146}},"velocity":1.7009284828147972,"acceleration":3.000000000000063,"curvature":0,"holonomicRotation":180.0,"angularVelocity":0.0,"holonomicAngularVelocity":0.0},{"time":0.5686848955939767,"pose":{"rotation":{"radians":0.0},"translation":{"x":2.2148241342467445,"y":4.445378345302146}},"velocity":1.7060546867819306,"acceleration":3.000000000000065,"curvature":0,"holonomicRotation":180.0,"angularVelocity":0.0,"holonomicAngularVelocity":0.0},{"time":0.570343177436771,"pose":{"rotation":{"radians":0.0},"translation":{"x":2.2176573786046543,"y":4.445378345302146}},"velocity":1.7110295323103135,"acceleration":3.000000000000067,"curvature":0,"holonomicRotation":180.0,"angularVelocity":0.0,"holonomicAngularVelocity":0.0},{"time":0.5719522824953832,"pose":{"rotation":{"radians":0.0},"translation":{"x":2.220414488709164,"y":4.445378345302146}},"velocity":1.71585684748615,"acceleration":2.999999999999862,"curvature":0,"holonomicRotation":180.0,"angularVelocity":0.0,"holonomicAngularVelocity":1.820530754387593e-11},{"time":0.573513459606064,"pose":{"rotation":{"radians":0.0},"translation":{"x":2.2230969010556207,"y":4.445378345302146}},"velocity":1.7205403788181923,"acceleration":2.999999999999929,"curvature":0,"holonomicRotation":180.00000000000003,"angularVelocity":0.0,"holonomicAngularVelocity":-1.876674173833046e-11},{"time":0.5750279318477933,"pose":{"rotation":{"radians":0.0},"translation":{"x":2.2257060521393717,"y":4.445378345302146}},"velocity":1.72508379554338,"acceleration":2.9999999999998535,"curvature":0,"holonomicRotation":180.0,"angularVelocity":0.0,"holonomicAngularVelocity":0.0},{"time":0.5764968978951622,"pose":{"rotation":{"radians":0.0},"translation":{"x":2.2282433784557636,"y":4.445378345302146}},"velocity":1.7294906936854866,"acceleration":2.9999999999999245,"curvature":0,"holonomicRotation":180.0,"angularVelocity":0.0,"holonomicAngularVelocity":0.0},{"time":0.5779215332946729,"pose":{"rotation":{"radians":0.0},"translation":{"x":2.2307103165001445,"y":4.445378345302146}},"velocity":1.7337645998840185,"acceleration":3.0,"curvature":0,"holonomicRotation":180.0,"angularVelocity":0.0,"holonomicAngularVelocity":2.0573699464258973e-11},{"time":0.5793029916697103,"pose":{"rotation":{"radians":0.0},"translation":{"x":2.2331083027678607,"y":4.445378345302146}},"velocity":1.7379089750091308,"acceleration":2.9999999999999196,"curvature":0,"holonomicRotation":180.00000000000003,"angularVelocity":0.0,"holonomicAngularVelocity":-2.1219507496181982e-11},{"time":0.5806424058590132,"pose":{"rotation":{"radians":0.0},"translation":{"x":2.2354387737542605,"y":4.445378345302146}},"velocity":1.7419272175770395,"acceleration":3.0000000000001656,"curvature":0,"holonomicRotation":180.0,"angularVelocity":0.0,"holonomicAngularVelocity":-2.1888393222249053e-11},{"time":0.5819408889930567,"pose":{"rotation":{"radians":0.0},"translation":{"x":2.2377031659546898,"y":4.445378345302146}},"velocity":1.74582266697917,"acceleration":2.9999999999999143,"curvature":0,"holonomicRotation":179.99999999999997,"angularVelocity":0.0,"holonomicAngularVelocity":2.258116873418733e-11},{"time":0.5831995355124184,"pose":{"rotation":{"radians":0.0},"translation":{"x":2.239902915864497,"y":4.445378345302146}},"velocity":1.7495986065372553,"acceleration":3.0000000000000884,"curvature":0,"holonomicRotation":180.0,"angularVelocity":0.0,"holonomicAngularVelocity":0.0},{"time":0.5844194221318464,"pose":{"rotation":{"radians":0.0},"translation":{"x":2.242039459979028,"y":4.445378345302146}},"velocity":1.753258266395539,"acceleration":2.999999999999818,"curvature":0,"holonomicRotation":180.0,"angularVelocity":0.0,"holonomicAngularVelocity":0.0},{"time":0.5856016087534736,"pose":{"rotation":{"radians":0.0},"translation":{"x":2.2441142347936305,"y":4.445378345302146}},"velocity":1.7568048262604206,"acceleration":3.0000000000000937,"curvature":0,"holonomicRotation":180.0,"angularVelocity":0.0,"holonomicAngularVelocity":0.0},{"time":0.5867471393323282,"pose":{"rotation":{"radians":0.0},"translation":{"x":2.246128676803652,"y":4.445378345302146}},"velocity":1.7602414179969845,"acceleration":2.999999999999903,"curvature":0,"holonomicRotation":180.0,"angularVelocity":0.0,"holonomicAngularVelocity":0.0},{"time":0.5878570426970565,"pose":{"rotation":{"radians":0.0},"translation":{"x":2.2480842225044393,"y":4.445378345302146}},"velocity":1.7635711280911692,"acceleration":2.9999999999999,"curvature":0,"holonomicRotation":180.0,"angularVelocity":0.0,"holonomicAngularVelocity":0.0},{"time":0.5889323333285378,"pose":{"rotation":{"radians":0.0},"translation":{"x":2.2499823083913397,"y":4.445378345302146}},"velocity":1.7667969999856128,"acceleration":2.9999999999997935,"curvature":0,"holonomicRotation":180.0,"angularVelocity":0.0,"holonomicAngularVelocity":0.0},{"time":0.5899740120988689,"pose":{"rotation":{"radians":0.0},"translation":{"x":2.2518243709597003,"y":4.445378345302146}},"velocity":1.7699220362966062,"acceleration":3.0,"curvature":0,"holonomicRotation":180.0,"angularVelocity":0.0,"holonomicAngularVelocity":0.0},{"time":0.5909830669730017,"pose":{"rotation":{"radians":0.0},"translation":{"x":2.253611846704869,"y":4.445378345302146}},"velocity":1.7729492009190049,"acceleration":3.0000000000002203,"curvature":0,"holonomicRotation":180.0,"angularVelocity":0.0,"holonomicAngularVelocity":0.0},{"time":0.5919604736751407,"pose":{"rotation":{"radians":0.0},"translation":{"x":2.2553461721221915,"y":4.445378345302146}},"velocity":1.775881421025422,"acceleration":3.0000000000001137,"curvature":0,"holonomicRotation":180.0,"angularVelocity":0.0,"holonomicAngularVelocity":0.0},{"time":0.5929071963218584,"pose":{"rotation":{"radians":0.0},"translation":{"x":2.257028783707016,"y":4.445378345302146}},"velocity":1.7787215889655752,"acceleration":3.0000000000002345,"curvature":0,"holonomicRotation":180.0,"angularVelocity":0.0,"holonomicAngularVelocity":0.0},{"time":0.5938241880237191,"pose":{"rotation":{"radians":0.0},"translation":{"x":2.25866111795469,"y":4.445378345302146}},"velocity":1.7814725640711573,"acceleration":3.0000000000001212,"curvature":0,"holonomicRotation":180.0,"angularVelocity":0.0,"holonomicAngularVelocity":0.0},{"time":0.594712391457088,"pose":{"rotation":{"radians":0.0},"translation":{"x":2.260244611360559,"y":4.445378345302146}},"velocity":1.7841371743712642,"acceleration":3.000000000000125,"curvature":0,"holonomicRotation":180.0,"angularVelocity":0.0,"holonomicAngularVelocity":0.0},{"time":0.5955727394076654,"pose":{"rotation":{"radians":0.0},"translation":{"x":2.2617807004199726,"y":4.445378345302146}},"velocity":1.7867182182229964,"acceleration":2.9999999999998708,"curvature":0,"holonomicRotation":180.0,"angularVelocity":0.0,"holonomicAngularVelocity":0.0},{"time":0.5964061552871668,"pose":{"rotation":{"radians":0.0},"translation":{"x":2.2632708216282764,"y":4.445378345302146}},"velocity":1.7892184658615007,"acceleration":3.0000000000002665,"curvature":0,"holonomicRotation":180.0,"angularVelocity":0.0,"holonomicAngularVelocity":0.0},{"time":0.5972135536244809,"pose":{"rotation":{"radians":0.0},"translation":{"x":2.2647164114808174,"y":4.445378345302146}},"velocity":1.791640660873443,"acceleration":2.9999999999998623,"curvature":0,"holonomicRotation":180.0,"angularVelocity":0.0,"holonomicAngularVelocity":0.0},{"time":0.5979958405325225,"pose":{"rotation":{"radians":0.0},"translation":{"x":2.2661189064729435,"y":4.445378345302146}},"velocity":1.7939875215975678,"acceleration":3.0,"curvature":0,"holonomicRotation":180.0,"angularVelocity":0.0,"holonomicAngularVelocity":0.0},{"time":0.5987539141519133,"pose":{"rotation":{"radians":0.0},"translation":{"x":2.2674797431000013,"y":4.445378345302146}},"velocity":1.7962617424557399,"acceleration":2.9999999999998535,"curvature":0,"holonomicRotation":180.0,"angularVelocity":0.0,"holonomicAngularVelocity":0.0},{"time":0.5994886650725446,"pose":{"rotation":{"radians":0.0},"translation":{"x":2.2688003578573386,"y":4.445378345302146}},"velocity":1.7984659952176338,"acceleration":2.999999999999849,"curvature":0,"holonomicRotation":180.0,"angularVelocity":0.0,"holonomicAngularVelocity":0.0},{"time":0.6002009767339915,"pose":{"rotation":{"radians":0.0},"translation":{"x":2.2700821872403023,"y":4.445378345302146}},"velocity":1.8006029302019744,"acceleration":2.9999999999996882,"curvature":0,"holonomicRotation":180.0,"angularVelocity":0.0,"holonomicAngularVelocity":0.0},{"time":0.6008917258056802,"pose":{"rotation":{"radians":0.0},"translation":{"x":2.271326667744239,"y":4.445378345302146}},"velocity":1.8026751774170402,"acceleration":2.9999999999998392,"curvature":0,"holonomicRotation":180.0,"angularVelocity":0.0,"holonomicAngularVelocity":0.0},{"time":0.6015617825476453,"pose":{"rotation":{"radians":0.0},"translation":{"x":2.272535235864497,"y":4.445378345302146}},"velocity":1.8046853476429354,"acceleration":3.0,"curvature":0,"holonomicRotation":180.0,"angularVelocity":0.0,"holonomicAngularVelocity":0.0},{"time":0.6022120111526483,"pose":{"rotation":{"radians":0.0},"translation":{"x":2.2737093280964222,"y":4.445378345302146}},"velocity":1.8066360334579445,"acceleration":2.9999999999998295,"curvature":0,"holonomicRotation":180.0,"angularVelocity":0.0,"holonomicAngularVelocity":0.0},{"time":0.6028432700703763,"pose":{"rotation":{"radians":0.0},"translation":{"x":2.274850380935363,"y":4.445378345302146}},"velocity":1.8085298102111285,"acceleration":3.0,"curvature":0,"holonomicRotation":180.0,"angularVelocity":0.0,"holonomicAngularVelocity":0.0},{"time":0.6034564123143827,"pose":{"rotation":{"radians":0.0},"translation":{"x":2.2759598308766655,"y":4.445378345302146}},"velocity":1.8103692369431477,"acceleration":2.999999999999819,"curvature":0,"holonomicRotation":180.0,"angularVelocity":0.0,"holonomicAngularVelocity":0.0},{"time":0.6040522857523908,"pose":{"rotation":{"radians":0.0},"translation":{"x":2.277039114415678,"y":4.445378345302146}},"velocity":1.812156857257172,"acceleration":3.0000000000003726,"curvature":0,"holonomicRotation":180.0,"angularVelocity":0.0,"holonomicAngularVelocity":0.0},{"time":0.6046317333805213,"pose":{"rotation":{"radians":0.0},"translation":{"x":2.278089668047747,"y":4.445378345302146}},"velocity":1.8138952001415638,"acceleration":3.0000000000001914,"curvature":0,"holonomicRotation":180.0,"angularVelocity":0.0,"holonomicAngularVelocity":0.0},{"time":0.6051955935819829,"pose":{"rotation":{"radians":0.0},"translation":{"x":2.279112928268219,"y":4.445378345302146}},"velocity":1.8155867807459487,"acceleration":3.0000000000001967,"curvature":0,"holonomicRotation":180.0,"angularVelocity":0.0,"holonomicAngularVelocity":0.0},{"time":0.6057447003707069,"pose":{"rotation":{"radians":0.0},"translation":{"x":2.2801103315724425,"y":4.445378345302146}},"velocity":1.8172341011121207,"acceleration":3.0,"curvature":0,"holonomicRotation":180.0,"angularVelocity":0.0,"holonomicAngularVelocity":0.0},{"time":0.606279883620383,"pose":{"rotation":{"radians":0.0},"translation":{"x":2.281083314455764,"y":4.445378345302146}},"velocity":1.8188396508611488,"acceleration":3.0,"curvature":0,"holonomicRotation":180.0,"angularVelocity":0.0,"holonomicAngularVelocity":0.0},{"time":0.6068019692793164,"pose":{"rotation":{"radians":0.0},"translation":{"x":2.282033313413531,"y":4.445378345302146}},"velocity":1.820405907837949,"acceleration":3.0,"curvature":0,"holonomicRotation":180.0,"angularVelocity":0.0,"holonomicAngularVelocity":0.0},{"time":0.6073117795714944,"pose":{"rotation":{"radians":0.0},"translation":{"x":2.2829617649410894,"y":4.445378345302146}},"velocity":1.8219353387144832,"acceleration":3.0000000000002176,"curvature":0,"holonomicRotation":180.0,"angularVelocity":0.0,"holonomicAngularVelocity":0.0},{"time":0.6078101331842272,"pose":{"rotation":{"radians":0.0},"translation":{"x":2.283870105533788,"y":4.445378345302146}},"velocity":1.8234303995526815,"acceleration":3.0,"curvature":0,"holonomicRotation":180.0,"angularVelocity":0.0,"holonomicAngularVelocity":0.0},{"time":0.6082978454426896,"pose":{"rotation":{"radians":0.0},"translation":{"x":2.2847597716869736,"y":4.445378345302146}},"velocity":1.8248935363280687,"acceleration":2.999999999999772,"curvature":0,"holonomicRotation":180.0,"angularVelocity":0.0,"holonomicAngularVelocity":0.0},{"time":0.6087757284716855,"pose":{"rotation":{"radians":0.0},"translation":{"x":2.285632199895993,"y":4.445378345302146}},"velocity":1.8263271854150565,"acceleration":3.0000000000002323,"curvature":0,"holonomicRotation":180.0,"angularVelocity":0.0,"holonomicAngularVelocity":0.0},{"time":0.6092445913449143,"pose":{"rotation":{"radians":0.0},"translation":{"x":2.2864888266561936,"y":4.445378345302146}},"velocity":1.8277337740347428,"acceleration":3.0,"curvature":0,"holonomicRotation":180.0,"angularVelocity":0.0,"holonomicAngularVelocity":0.0},{"time":0.6097052402220142,"pose":{"rotation":{"radians":0.0},"translation":{"x":2.2873310884629223,"y":4.445378345302146}},"velocity":1.8291157206660427,"acceleration":3.0,"curvature":0,"holonomicRotation":180.0,"angularVelocity":0.0,"holonomicAngularVelocity":0.0},{"time":0.6101584784736287,"pose":{"rotation":{"radians":0.0},"translation":{"x":2.2881604218115266,"y":4.445378345302146}},"velocity":1.8304754354208859,"acceleration":2.99999999999951,"curvature":0,"holonomicRotation":180.0,"angularVelocity":0.0,"holonomicAngularVelocity":0.0},{"time":0.6106052792703223,"pose":{"rotation":{"radians":0.0},"translation":{"x":2.2889782631973534,"y":4.445378345302146}},"velocity":1.8304015902201245,"acceleration":-0.16527544558523752,"curvature":0,"holonomicRotation":180.0,"angularVelocity":0.0,"holonomicAngularVelocity":0.0},{"time":0.6110467552143052,"pose":{"rotation":{"radians":0.0},"translation":{"x":2.28978604911575,"y":4.445378345302146}},"velocity":1.8290771623881756,"acceleration":-3.0000000000002514,"curvature":0,"holonomicRotation":180.0,"angularVelocity":0.0,"holonomicAngularVelocity":0.0},{"time":0.6114838354651942,"pose":{"rotation":{"radians":0.0},"translation":{"x":2.2905852160620634,"y":4.445378345302146}},"velocity":1.8277659216355084,"acceleration":-3.0,"curvature":0,"holonomicRotation":180.0,"angularVelocity":0.0,"holonomicAngularVelocity":0.0},{"time":0.6119172970444976,"pose":{"rotation":{"radians":0.0},"translation":{"x":2.2913772005316413,"y":4.445378345302146}},"velocity":1.8264655368975984,"acceleration":-3.0,"curvature":0,"holonomicRotation":180.0,"angularVelocity":0.0,"holonomicAngularVelocity":0.0},{"time":0.6123479192629532,"pose":{"rotation":{"radians":0.0},"translation":{"x":2.29216343901983,"y":4.445378345302146}},"velocity":1.8251736702422316,"acceleration":-3.0,"curvature":0,"holonomicRotation":180.0,"angularVelocity":0.0,"holonomicAngularVelocity":0.0},{"time":0.6127764836873142,"pose":{"rotation":{"radians":0.0},"translation":{"x":2.292945368021978,"y":4.445378345302146}},"velocity":1.8238879769691485,"acceleration":-3.000000000000259,"curvature":0,"holonomicRotation":180.0,"angularVelocity":0.0,"holonomicAngularVelocity":0.0},{"time":0.6132037741168584,"pose":{"rotation":{"radians":0.0},"translation":{"x":2.2937244240334307,"y":4.445378345302146}},"velocity":1.8226061056805158,"acceleration":-2.99999999999974,"curvature":0,"holonomicRotation":180.0,"angularVelocity":0.0,"holonomicAngularVelocity":0.0},{"time":0.613630576569776,"pose":{"rotation":{"radians":0.0},"translation":{"x":2.294502043549537,"y":4.445378345302146}},"velocity":1.8213256983217632,"acceleration":-2.9999999999997398,"curvature":0,"holonomicRotation":180.0,"angularVelocity":0.0,"holonomicAngularVelocity":0.0},{"time":0.6140576792795822,"pose":{"rotation":{"radians":0.0},"translation":{"x":2.2952796630656427,"y":4.445378345302146}},"velocity":1.8200443901923447,"acceleration":-3.0,"curvature":0,"holonomicRotation":180.0,"angularVelocity":0.0,"holonomicAngularVelocity":0.0},{"time":0.6144858727017114,"pose":{"rotation":{"radians":0.0},"translation":{"x":2.296058719077096,"y":4.445378345302146}},"velocity":1.8187598099259572,"acceleration":-2.9999999999997407,"curvature":0,"holonomicRotation":180.0,"angularVelocity":0.0,"holonomicAngularVelocity":0.0},{"time":0.6149159495304362,"pose":{"rotation":{"radians":0.0},"translation":{"x":2.296840648079243,"y":4.445378345302146}},"velocity":1.8174695794397828,"acceleration":-3.000000000000258,"curvature":0,"holonomicRotation":180.0,"angularVelocity":0.0,"holonomicAngularVelocity":0.0},{"time":0.6153487047262731,"pose":{"rotation":{"radians":0.0},"translation":{"x":2.297626886567432,"y":4.445378345302146}},"velocity":1.816171313852272,"acceleration":-3.0,"curvature":0,"holonomicRotation":180.0,"angularVelocity":0.0,"holonomicAngularVelocity":0.0},{"time":0.6157849355540249,"pose":{"rotation":{"radians":0.0},"translation":{"x":2.2984188710370104,"y":4.445378345302146}},"velocity":1.8148626213690164,"acceleration":-3.0000000000002545,"curvature":0,"holonomicRotation":180.0,"angularVelocity":0.0,"holonomicAngularVelocity":0.0},{"time":0.6162254416316237,"pose":{"rotation":{"radians":0.0},"translation":{"x":2.299218037983324,"y":4.445378345302146}},"velocity":1.8135411031362199,"acceleration":-3.0000000000002522,"curvature":0,"holonomicRotation":180.0,"angularVelocity":0.0,"holonomicAngularVelocity":0.0},{"time":0.6166710249899457,"pose":{"rotation":{"radians":0.0},"translation":{"x":2.3000258239017204,"y":4.445378345302146}},"velocity":1.812204353061254,"acceleration":-2.999999999999751,"curvature":0,"holonomicRotation":180.0,"angularVelocity":0.0,"holonomicAngularVelocity":0.0},{"time":0.6171224901437637,"pose":{"rotation":{"radians":0.0},"translation":{"x":2.3008436652875472,"y":4.445378345302146}},"velocity":1.8108499575997998,"acceleration":-3.000000000000246,"curvature":0,"holonomicRotation":180.0,"angularVelocity":0.0,"holonomicAngularVelocity":0.0},{"time":0.6175806441740276,"pose":{"rotation":{"radians":0.0},"translation":{"x":2.3016729986361515,"y":4.445378345302146}},"velocity":1.8094754955090084,"acceleration":-2.9999999999997575,"curvature":0,"holonomicRotation":180.0,"angularVelocity":0.0,"holonomicAngularVelocity":0.0},{"time":0.6180462968216608,"pose":{"rotation":{"radians":0.0},"translation":{"x":2.3025152604428802,"y":4.445378345302146}},"velocity":1.8080785375661088,"acceleration":-3.0,"curvature":0,"holonomicRotation":180.0,"angularVelocity":0.0,"holonomicAngularVelocity":0.0},{"time":0.6185202605930791,"pose":{"rotation":{"radians":0.0},"translation":{"x":2.3033718872030806,"y":4.445378345302146}},"velocity":1.8066566462518538,"acceleration":-3.000000000000234,"curvature":0,"holonomicRotation":180.0,"angularVelocity":0.0,"holonomicAngularVelocity":0.0},{"time":0.6190033508776467,"pose":{"rotation":{"radians":0.0},"translation":{"x":2.3042443154120997,"y":4.445378345302146}},"velocity":1.805207375398151,"acceleration":-3.0,"curvature":0,"holonomicRotation":180.0,"angularVelocity":0.0,"holonomicAngularVelocity":0.0},{"time":0.6194963860773016,"pose":{"rotation":{"radians":0.0},"translation":{"x":2.3051339815652856,"y":4.445378345302146}},"velocity":1.803728269799186,"acceleration":-3.000000000000225,"curvature":0,"holonomicRotation":180.0,"angularVelocity":0.0,"holonomicAngularVelocity":0.0},{"time":0.6200001877485954,"pose":{"rotation":{"radians":0.0},"translation":{"x":2.3060423221579844,"y":4.445378345302146}},"velocity":1.8022168647853045,"acceleration":-3.0000000000002203,"curvature":0,"holonomicRotation":180.0,"angularVelocity":0.0,"holonomicAngularVelocity":0.0},{"time":0.6205155807574162,"pose":{"rotation":{"radians":0.0},"translation":{"x":2.3069707736855434,"y":4.445378345302146}},"velocity":1.8006706857588421,"acceleration":-3.0000000000002154,"curvature":0,"holonomicRotation":180.0,"angularVelocity":0.0,"holonomicAngularVelocity":0.0},{"time":0.6210433934466745,"pose":{"rotation":{"radians":0.0},"translation":{"x":2.30792077264331,"y":4.445378345302146}},"velocity":1.7990872476910673,"acceleration":-3.0,"curvature":0,"holonomicRotation":180.0,"angularVelocity":0.0,"holonomicAngularVelocity":0.0},{"time":0.6215844578172603,"pose":{"rotation":{"radians":0.0},"translation":{"x":2.3088937555266313,"y":4.445378345302146}},"velocity":1.7974640545793097,"acceleration":-3.0,"curvature":0,"holonomicRotation":180.0,"angularVelocity":0.0,"holonomicAngularVelocity":0.0},{"time":0.6221396097226009,"pose":{"rotation":{"radians":0.0},"translation":{"x":2.309891158830855,"y":4.445378345302146}},"velocity":1.7957985988632883,"acceleration":-2.9999999999998,"curvature":0,"holonomicRotation":180.0,"angularVelocity":0.0,"holonomicAngularVelocity":0.0},{"time":0.6227096890771711,"pose":{"rotation":{"radians":0.0},"translation":{"x":2.3109144190513273,"y":4.445378345302146}},"velocity":1.7940883607995777,"acceleration":-3.0,"curvature":0,"holonomicRotation":180.0,"angularVelocity":0.0,"holonomicAngularVelocity":0.0},{"time":0.6232955400793455,"pose":{"rotation":{"radians":0.0},"translation":{"x":2.311964972683396,"y":4.445378345302146}},"velocity":1.7923308077930542,"acceleration":-3.0000000000001896,"curvature":0,"holonomicRotation":180.0,"angularVelocity":0.0,"holonomicAngularVelocity":0.0},{"time":0.6238980114489966,"pose":{"rotation":{"radians":0.0},"translation":{"x":2.3130442562224083,"y":4.445378345302146}},"velocity":1.790523393684101,"acceleration":-3.0,"curvature":0,"holonomicRotation":180.0,"angularVelocity":0.0,"holonomicAngularVelocity":0.0},{"time":0.6245179566802922,"pose":{"rotation":{"radians":0.0},"translation":{"x":2.314153706163711,"y":4.445378345302146}},"velocity":1.7886635579902141,"acceleration":-3.0,"curvature":0,"holonomicRotation":180.0,"angularVelocity":0.0,"holonomicAngularVelocity":0.0},{"time":0.6251562343101684,"pose":{"rotation":{"radians":0.0},"translation":{"x":2.315294759002652,"y":4.445378345302146}},"velocity":1.7867487251005854,"acceleration":-3.000000000000174,"curvature":0,"holonomicRotation":180.0,"angularVelocity":0.0,"holonomicAngularVelocity":0.0},{"time":0.6258137082030005,"pose":{"rotation":{"radians":0.0},"translation":{"x":2.316468851234577,"y":4.445378345302146}},"velocity":1.7847763034220891,"acceleration":-2.9999999999998312,"curvature":0,"holonomicRotation":180.0,"angularVelocity":0.0,"holonomicAngularVelocity":0.0},{"time":0.626491247852033,"pose":{"rotation":{"radians":0.0},"translation":{"x":2.317677419354835,"y":4.445378345302146}},"velocity":1.7827436844749918,"acceleration":-2.999999999999836,"curvature":0,"holonomicRotation":180.0,"angularVelocity":0.0,"holonomicAngularVelocity":0.0},{"time":0.6271897286981689,"pose":{"rotation":{"radians":0.0},"translation":{"x":2.318921899858772,"y":4.445378345302146}},"velocity":1.780648241936584,"acceleration":-3.0,"curvature":0,"holonomicRotation":180.0,"angularVelocity":0.0,"holonomicAngularVelocity":0.0},{"time":0.6279100324667827,"pose":{"rotation":{"radians":0.0},"translation":{"x":2.3202037292417357,"y":4.445378345302146}},"velocity":1.778487330630743,"acceleration":-2.999999999999846,"curvature":0,"holonomicRotation":180.0,"angularVelocity":0.0,"holonomicAngularVelocity":0.0},{"time":0.6286530475232519,"pose":{"rotation":{"radians":0.0},"translation":{"x":2.321524343999073,"y":4.445378345302146}},"velocity":1.7762582854613351,"acceleration":-3.000000000000149,"curvature":0,"holonomicRotation":180.0,"angularVelocity":0.0,"holonomicAngularVelocity":0.0},{"time":0.629419669247979,"pose":{"rotation":{"radians":0.0},"translation":{"x":2.322885180626131,"y":4.445378345302146}},"velocity":1.773958420287154,"acceleration":-3.0,"curvature":0,"holonomicRotation":180.0,"angularVelocity":0.0,"holonomicAngularVelocity":0.0},{"time":0.6302108004317211,"pose":{"rotation":{"radians":0.0},"translation":{"x":2.324287675618257,"y":4.445378345302146}},"velocity":1.7715850267359277,"acceleration":-3.0,"curvature":0,"holonomicRotation":180.0,"angularVelocity":0.0,"holonomicAngularVelocity":0.0},{"time":0.6310273516921187,"pose":{"rotation":{"radians":0.0},"translation":{"x":2.3257332654707983,"y":4.445378345302146}},"velocity":1.769135372954735,"acceleration":-2.999999999999864,"curvature":0,"holonomicRotation":180.0,"angularVelocity":0.0,"holonomicAngularVelocity":0.0},{"time":0.6318702419123837,"pose":{"rotation":{"radians":0.0},"translation":{"x":2.3272233866791017,"y":4.445378345302146}},"velocity":1.7666067022939398,"acceleration":-3.0,"curvature":0,"holonomicRotation":180.0,"angularVelocity":0.0,"holonomicAngularVelocity":0.0},{"time":0.6327403987031837,"pose":{"rotation":{"radians":0.0},"translation":{"x":2.3287594757385146,"y":4.445378345302146}},"velocity":1.7639962319215399,"acceleration":-3.0000000000001275,"curvature":0,"holonomicRotation":180.0,"angularVelocity":0.0,"holonomicAngularVelocity":0.0},{"time":0.6336387588888392,"pose":{"rotation":{"radians":0.0},"translation":{"x":2.3303429691443847,"y":4.445378345302146}},"velocity":1.761301151364573,"acceleration":-3.0,"curvature":0,"holonomicRotation":180.0,"angularVelocity":0.0,"holonomicAngularVelocity":0.0},{"time":0.6345662690190464,"pose":{"rotation":{"radians":0.0},"translation":{"x":2.3319753033920585,"y":4.445378345302146}},"velocity":1.7585186209739514,"acceleration":-3.00000000000012,"curvature":0,"holonomicRotation":180.0,"angularVelocity":0.0,"holonomicAngularVelocity":0.0},{"time":0.63552388590743,"pose":{"rotation":{"radians":0.0},"translation":{"x":2.333657914976883,"y":4.445378345302146}},"velocity":1.7556457703088006,"acceleration":-3.0,"curvature":0,"holonomicRotation":180.0,"angularVelocity":0.0,"holonomicAngularVelocity":0.0},{"time":0.6365125771983394,"pose":{"rotation":{"radians":0.0},"translation":{"x":2.335392240394206,"y":4.445378345302146}},"velocity":1.7526796964360725,"acceleration":-3.0,"curvature":0,"holonomicRotation":180.0,"angularVelocity":0.0,"holonomicAngularVelocity":0.0},{"time":0.6375333219634091,"pose":{"rotation":{"radians":0.0},"translation":{"x":2.337179716139374,"y":4.445378345302146}},"velocity":1.7496174621408633,"acceleration":-3.0000000000002176,"curvature":0,"holonomicRotation":180.0,"angularVelocity":0.0,"holonomicAngularVelocity":0.0},{"time":0.6385871113295413,"pose":{"rotation":{"radians":0.0},"translation":{"x":2.339021778707735,"y":4.445378345302146}},"velocity":1.7464560940424667,"acceleration":-3.0,"curvature":0,"holonomicRotation":180.0,"angularVelocity":0.0,"holonomicAngularVelocity":0.0},{"time":0.6396749491400847,"pose":{"rotation":{"radians":0.0},"translation":{"x":2.3409198645946354,"y":4.445378345302146}},"velocity":1.7431925806108362,"acceleration":-3.0000000000002043,"curvature":0,"holonomicRotation":180.0,"angularVelocity":0.0,"holonomicAngularVelocity":0.0},{"time":0.6407978526511495,"pose":{"rotation":{"radians":0.0},"translation":{"x":2.342875410295423,"y":4.445378345302146}},"velocity":1.7398238700776416,"acceleration":-3.000000000000099,"curvature":0,"holonomicRotation":180.0,"angularVelocity":0.0,"holonomicAngularVelocity":0.0},{"time":0.6419568532651408,"pose":{"rotation":{"radians":0.0},"translation":{"x":2.3448898523054447,"y":4.445378345302146}},"velocity":1.7363468682356678,"acceleration":-2.999999999999904,"curvature":0,"holonomicRotation":180.0,"angularVelocity":0.0,"holonomicAngularVelocity":0.0},{"time":0.6431529973037768,"pose":{"rotation":{"radians":0.0},"translation":{"x":2.3469646271200473,"y":4.445378345302146}},"velocity":1.7327584361197597,"acceleration":-3.000000000000093,"curvature":0,"holonomicRotation":180.0,"angularVelocity":0.0,"holonomicAngularVelocity":0.0},{"time":0.6443873468230465,"pose":{"rotation":{"radians":0.0},"translation":{"x":2.3491011712345786,"y":4.445378345302146}},"velocity":1.7290553875619505,"acceleration":-3.0,"curvature":0,"holonomicRotation":180.0,"angularVelocity":0.0,"holonomicAngularVelocity":0.0},{"time":0.6456609804727598,"pose":{"rotation":{"radians":0.0},"translation":{"x":2.351300921144385,"y":4.445378345302146}},"velocity":1.7252344866128109,"acceleration":-3.0,"curvature":0,"holonomicRotation":180.0,"angularVelocity":0.0,"holonomicAngularVelocity":0.0},{"time":0.6469749944035826,"pose":{"rotation":{"radians":0.0},"translation":{"x":2.3535653133448147,"y":4.445378345302146}},"velocity":1.7212924448203422,"acceleration":-3.0000000000000844,"curvature":0,"holonomicRotation":180.0,"angularVelocity":0.0,"holonomicAngularVelocity":0.0},{"time":0.6483305032246821,"pose":{"rotation":{"radians":0.0},"translation":{"x":2.3558957843312145,"y":4.445378345302146}},"velocity":1.7172259183570435,"acceleration":-3.000000000000164,"curvature":0,"holonomicRotation":180.0,"angularVelocity":0.0,"holonomicAngularVelocity":0.0},{"time":0.6497286410153907,"pose":{"rotation":{"radians":0.0},"translation":{"x":2.358293770598931,"y":4.445378345302146}},"velocity":1.7130315049849176,"acceleration":-3.0,"curvature":0,"holonomicRotation":180.0,"angularVelocity":0.0,"holonomicAngularVelocity":0.0},{"time":0.6511705623945883,"pose":{"rotation":{"radians":0.0},"translation":{"x":2.360760708643312,"y":4.445378345302146}},"velocity":1.7087057408473252,"acceleration":-2.999999999999923,"curvature":0,"holonomicRotation":180.0,"angularVelocity":0.0,"holonomicAngularVelocity":0.0},{"time":0.652657443651827,"pose":{"rotation":{"radians":0.0},"translation":{"x":2.3632980349597044,"y":4.445378345302146}},"velocity":1.7042450970756091,"acceleration":-2.9999999999999254,"curvature":0,"holonomicRotation":180.0,"angularVelocity":0.0,"holonomicAngularVelocity":0.0},{"time":0.6541904839445895,"pose":{"rotation":{"radians":0.0},"translation":{"x":2.3659071860434553,"y":4.445378345302146}},"velocity":1.6996459761973217,"acceleration":-3.0,"curvature":0,"holonomicRotation":180.0,"angularVelocity":0.0,"holonomicAngularVelocity":0.0},{"time":0.6557709065664592,"pose":{"rotation":{"radians":0.0},"translation":{"x":2.368589598389912,"y":4.445378345302146}},"velocity":1.6949047083317124,"acceleration":-3.00000000000007,"curvature":0,"holonomicRotation":180.0,"angularVelocity":0.0,"holonomicAngularVelocity":0.0},{"time":0.657399960291424,"pose":{"rotation":{"radians":0.0},"translation":{"x":2.3713467084944218,"y":4.445378345302146}},"velocity":1.690017547156818,"acceleration":-3.0,"curvature":0,"holonomicRotation":180.0,"angularVelocity":0.0,"holonomicAngularVelocity":0.0},{"time":0.6590789208000101,"pose":{"rotation":{"radians":0.0},"translation":{"x":2.3741799528523315,"y":4.445378345302146}},"velocity":1.6849806656310597,"acceleration":-3.0,"curvature":0,"holonomicRotation":180.0,"angularVelocity":0.0,"holonomicAngularVelocity":0.0},{"time":0.6608090921934852,"pose":{"rotation":{"radians":0.0},"translation":{"x":2.3770907679589888,"y":4.445378345302146}},"velocity":1.6797901514506346,"acceleration":-2.999999999999936,"curvature":0,"holonomicRotation":180.0,"angularVelocity":0.0,"holonomicAngularVelocity":0.0},{"time":0.662591808602949,"pose":{"rotation":{"radians":0.0},"translation":{"x":2.3800805903097406,"y":4.445378345302146}},"velocity":1.6744420022222433,"acceleration":-2.999999999999938,"curvature":0,"holonomicRotation":180.0,"angularVelocity":0.0,"holonomicAngularVelocity":0.0},{"time":0.6644284359007941,"pose":{"rotation":{"radians":0.0},"translation":{"x":2.3831508563999337,"y":4.445378345302146}},"velocity":1.6689321203287077,"acceleration":-3.0,"curvature":0,"holonomicRotation":180.0,"angularVelocity":0.0,"holonomicAngularVelocity":0.0},{"time":0.666320373522744,"pose":{"rotation":{"radians":0.0},"translation":{"x":2.386303002724916,"y":4.445378345302146}},"velocity":1.6632563074628584,"acceleration":-2.9999999999999414,"curvature":0,"holonomicRotation":180.0,"angularVelocity":0.0,"holonomicAngularVelocity":0.0},{"time":0.6682690564094793,"pose":{"rotation":{"radians":0.0},"translation":{"x":2.389538465780034,"y":4.445378345302146}},"velocity":1.6574102588026522,"acceleration":-3.000000000000057,"curvature":0,"holonomicRotation":180.0,"angularVelocity":0.0,"holonomicAngularVelocity":0.0},{"time":0.6702759570777803,"pose":{"rotation":{"radians":0.0},"translation":{"x":2.3928586820606355,"y":4.445378345302146}},"velocity":1.651389556797749,"acceleration":-3.0000000000001106,"curvature":0,"holonomicRotation":180.0,"angularVelocity":0.0,"holonomicAngularVelocity":0.0},{"time":0.6723425878321019,"pose":{"rotation":{"radians":0.0},"translation":{"x":2.396265088062067,"y":4.445378345302146}},"velocity":1.6451896645347843,"acceleration":-3.0,"curvature":0,"holonomicRotation":180.0,"angularVelocity":0.0,"holonomicAngularVelocity":0.0},{"time":0.674470503128642,"pose":{"rotation":{"radians":0.0},"translation":{"x":2.3997591202796764,"y":4.445378345302146}},"velocity":1.638805918645164,"acceleration":-3.0,"curvature":0,"holonomicRotation":180.0,"angularVelocity":0.0,"holonomicAngularVelocity":0.0},{"time":0.6766613021052139,"pose":{"rotation":{"radians":0.0},"translation":{"x":2.4033422152088106,"y":4.445378345302146}},"velocity":1.6322335217154482,"acceleration":-3.0,"curvature":0,"holonomicRotation":180.0,"angularVelocity":0.0,"holonomicAngularVelocity":0.0},{"time":0.6789166312916561,"pose":{"rotation":{"radians":0.0},"translation":{"x":2.407015809344816,"y":4.445378345302146}},"velocity":1.6254675341561218,"acceleration":-2.9999999999999014,"curvature":0,"holonomicRotation":180.0,"angularVelocity":0.0,"holonomicAngularVelocity":0.0},{"time":0.681238187517106,"pose":{"rotation":{"radians":0.0},"translation":{"x":2.410781339183041,"y":4.445378345302146}},"velocity":1.6185028654797722,"acceleration":-3.000000000000048,"curvature":0,"holonomicRotation":180.0,"angularVelocity":0.0,"holonomicAngularVelocity":0.0},{"time":0.6836277210322503,"pose":{"rotation":{"radians":0.0},"translation":{"x":2.414640241218832,"y":4.445378345302146}},"velocity":1.611334264934339,"acceleration":-3.0000000000000466,"curvature":0,"holonomicRotation":180.0,"angularVelocity":0.0,"holonomicAngularVelocity":0.0},{"time":0.6860870388667049,"pose":{"rotation":{"radians":0.0},"translation":{"x":2.4185939519475363,"y":4.445378345302146}},"velocity":1.6039563114309752,"acceleration":-3.00000000000009,"curvature":0,"holonomicRotation":180.0,"angularVelocity":0.0,"holonomicAngularVelocity":0.0},{"time":0.6886180084439526,"pose":{"rotation":{"radians":0.0},"translation":{"x":2.4226439078645012,"y":4.445378345302146}},"velocity":1.596363402699232,"acceleration":-3.0,"curvature":0,"holonomicRotation":180.0,"angularVelocity":0.0,"holonomicAngularVelocity":0.0},{"time":0.6912225614788757,"pose":{"rotation":{"radians":0.0},"translation":{"x":2.426791545465074,"y":4.445378345302146}},"velocity":1.5885497435944627,"acceleration":-2.9999999999999574,"curvature":0,"holonomicRotation":180.0,"angularVelocity":0.0,"holonomicAngularVelocity":0.0},{"time":0.6939026981858611,"pose":{"rotation":{"radians":0.0},"translation":{"x":2.4310383012446017,"y":4.445378345302146}},"velocity":1.5805093334735063,"acceleration":-3.0000000000000413,"curvature":0,"holonomicRotation":180.0,"angularVelocity":0.0,"holonomicAngularVelocity":0.0},{"time":0.6966604918288233,"pose":{"rotation":{"radians":0.0},"translation":{"x":2.4353856116984316,"y":4.445378345302146}},"velocity":1.57223595254462,"acceleration":-3.0,"curvature":0,"holonomicRotation":180.0,"angularVelocity":0.0,"holonomicAngularVelocity":0.0},{"time":0.699498093648313,"pose":{"rotation":{"radians":0.0},"translation":{"x":2.4398349133219104,"y":4.445378345302146}},"velocity":1.5637231470861508,"acceleration":-3.000000000000039,"curvature":0,"holonomicRotation":180.0,"angularVelocity":0.0,"holonomicAngularVelocity":0.0},{"time":0.7024177382052738,"pose":{"rotation":{"radians":0.0},"translation":{"x":2.4443876426103857,"y":4.445378345302146}},"velocity":1.5549642134152681,"acceleration":-3.000000000000076,"curvature":0,"holonomicRotation":180.0,"angularVelocity":0.0,"holonomicAngularVelocity":0.0},{"time":0.7054217491860272,"pose":{"rotation":{"radians":0.0},"translation":{"x":2.449045236059205,"y":4.445378345302146}},"velocity":1.5459521804730079,"acceleration":-3.0,"curvature":0,"holonomicRotation":180.0,"angularVelocity":0.0,"holonomicAngularVelocity":0.0},{"time":0.7085125457188528,"pose":{"rotation":{"radians":0.0},"translation":{"x":2.453809130163714,"y":4.445378345302146}},"velocity":1.536679790874531,"acceleration":-2.999999999999964,"curvature":0,"holonomicRotation":180.0,"angularVelocity":0.0,"holonomicAngularVelocity":0.0},{"time":0.7116926492591992,"pose":{"rotation":{"radians":0.0},"translation":{"x":2.458680761419262,"y":4.445378345302146}},"velocity":1.5271394802534919,"acceleration":-3.000000000000035,"curvature":0,"holonomicRotation":180.0,"angularVelocity":0.0,"holonomicAngularVelocity":0.0},{"time":0.7149646911082491,"pose":{"rotation":{"radians":0.0},"translation":{"x":2.463661566321195,"y":4.445378345302146}},"velocity":1.517323354706342,"acceleration":-3.0,"curvature":0,"holonomicRotation":180.0,"angularVelocity":0.0,"holonomicAngularVelocity":0.0},{"time":0.7183314206385203,"pose":{"rotation":{"radians":0.0},"translation":{"x":2.46875298136486,"y":4.445378345302146}},"velocity":1.5072231661155286,"acceleration":-2.999999999999967,"curvature":0,"holonomicRotation":180.0,"angularVelocity":0.0,"holonomicAngularVelocity":0.0},{"time":0.721795714310552,"pose":{"rotation":{"radians":0.0},"translation":{"x":2.4739564430456045,"y":4.445378345302146}},"velocity":1.4968302850994333,"acceleration":-3.000000000000064,"curvature":0,"holonomicRotation":180.0,"angularVelocity":0.0,"holonomicAngularVelocity":0.0},{"time":0.7253605855768589,"pose":{"rotation":{"radians":0.0},"translation":{"x":2.4792733878587754,"y":4.445378345302146}},"velocity":1.4861356713005127,"acceleration":-2.999999999999969,"curvature":0,"holonomicRotation":180.0,"angularVelocity":0.0,"holonomicAngularVelocity":0.0},{"time":0.7290291957835211,"pose":{"rotation":{"radians":0.0},"translation":{"x":2.4847052522997206,"y":4.445378345302146}},"velocity":1.475129840680526,"acceleration":-3.00000000000003,"curvature":0,"holonomicRotation":180.0,"angularVelocity":0.0,"holonomicAngularVelocity":0.0},{"time":0.7328048661964366,"pose":{"rotation":{"radians":0.0},"translation":{"x":2.4902534728637864,"y":4.445378345302146}},"velocity":1.4638028294417795,"acceleration":-3.0,"curvature":0,"holonomicRotation":180.0,"angularVelocity":0.0,"holonomicAngularVelocity":0.0},{"time":0.7366910912989143,"pose":{"rotation":{"radians":0.0},"translation":{"x":2.4959194860463203,"y":4.445378345302146}},"velocity":1.4521441541343463,"acceleration":-3.0000000000000284,"curvature":0,"holonomicRotation":180.0,"angularVelocity":0.0,"holonomicAngularVelocity":0.0},{"time":0.7406915535305116,"pose":{"rotation":{"radians":0.0},"translation":{"x":2.50170472834267,"y":4.445378345302146}},"velocity":1.4401427674395546,"acceleration":-2.999999999999917,"curvature":0,"holonomicRotation":180.0,"angularVelocity":0.0,"holonomicAngularVelocity":0.0},{"time":0.7448101396646305,"pose":{"rotation":{"radians":0.0},"translation":{"x":2.507610636248182,"y":4.445378345302146}},"velocity":1.4277870090371978,"acceleration":-3.0000000000000537,"curvature":0,"holonomicRotation":180.0,"angularVelocity":0.0,"holonomicAngularVelocity":0.0},{"time":0.7490509590553052,"pose":{"rotation":{"radians":0.0},"translation":{"x":2.5136386462582037,"y":4.445378345302146}},"velocity":1.4150645508651738,"acceleration":-3.0,"curvature":0,"holonomicRotation":180.0,"angularVelocity":0.0,"holonomicAngularVelocity":0.0},{"time":0.7534183640230347,"pose":{"rotation":{"radians":0.0},"translation":{"x":2.519790194868082,"y":4.445378345302146}},"velocity":1.4019623359619848,"acceleration":-3.0000000000000506,"curvature":0,"holonomicRotation":180.0,"angularVelocity":0.0,"holonomicAngularVelocity":0.0},{"time":0.757916972696966,"pose":{"rotation":{"radians":0.0},"translation":{"x":2.526066718573164,"y":4.445378345302146}},"velocity":1.3884665099401912,"acceleration":-2.999999999999975,"curvature":0,"holonomicRotation":180.0,"angularVelocity":0.0,"holonomicAngularVelocity":0.0},{"time":0.7625516946880735,"pose":{"rotation":{"radians":0.0},"translation":{"x":2.5324696538687976,"y":4.445378345302146}},"velocity":1.3745623439668686,"acceleration":-3.000000000000024,"curvature":0,"holonomicRotation":180.0,"angularVelocity":0.0,"holonomicAngularVelocity":0.0},{"time":0.7673277600376603,"pose":{"rotation":{"radians":0.0},"translation":{"x":2.5390004372503294,"y":4.445378345302146}},"velocity":1.360234147918108,"acceleration":-3.000000000000023,"curvature":0,"holonomicRotation":180.0,"angularVelocity":0.0,"holonomicAngularVelocity":0.0},{"time":0.772250751970619,"pose":{"rotation":{"radians":0.0},"translation":{"x":2.545660505213107,"y":4.445378345302146}},"velocity":1.3454651721192321,"acceleration":-2.9999999999999774,"curvature":0,"holonomicRotation":180.0,"angularVelocity":0.0,"holonomicAngularVelocity":0.0},{"time":0.7773266440873837,"pose":{"rotation":{"radians":0.0},"translation":{"x":2.552451294252477,"y":4.445378345302146}},"velocity":1.330237495768938,"acceleration":-2.9999999999999782,"curvature":0,"holonomicRotation":180.0,"angularVelocity":0.0,"holonomicAngularVelocity":0.0},{"time":0.7825618427576487,"pose":{"rotation":{"radians":0.0},"translation":{"x":2.5593742408637876,"y":4.445378345302146}},"velocity":1.3145318997581428,"acceleration":-3.0000000000000426,"curvature":0,"holonomicRotation":180.0,"angularVelocity":0.0,"holonomicAngularVelocity":0.0},{"time":0.7879632356394018,"pose":{"rotation":{"radians":0.0},"translation":{"x":2.566430781542384,"y":4.445378345302146}},"velocity":1.2983277211128834,"acceleration":-3.0,"curvature":0,"holonomicRotation":180.0,"angularVelocity":0.0,"holonomicAngularVelocity":0.0},{"time":0.7935382474476845,"pose":{"rotation":{"radians":0.0},"translation":{"x":2.5736223527836155,"y":4.445378345302146}},"velocity":1.2816026856880351,"acceleration":-3.00000000000004,"curvature":0,"holonomicRotation":180.0,"angularVelocity":0.0,"holonomicAngularVelocity":0.0},{"time":0.7992949043505195,"pose":{"rotation":{"radians":0.0},"translation":{"x":2.580950391082828,"y":4.445378345302146}},"velocity":1.2643327149795303,"acceleration":-2.999999999999981,"curvature":0,"holonomicRotation":180.0,"angularVelocity":0.0,"holonomicAngularVelocity":0.0},{"time":0.8052419086907476,"pose":{"rotation":{"radians":0.0},"translation":{"x":2.5884163329353695,"y":4.445378345302146}},"velocity":1.246491701958846,"acceleration":-3.0,"curvature":0,"holonomicRotation":180.0,"angularVelocity":0.0,"holonomicAngularVelocity":0.0},{"time":0.8113887261435826,"pose":{"rotation":{"radians":0.0},"translation":{"x":2.5960216148365864,"y":4.445378345302146}},"velocity":1.228051249600341,"acceleration":-3.0,"curvature":0,"holonomicRotation":180.0,"angularVelocity":0.0,"holonomicAngularVelocity":0.0},{"time":0.8177456879502644,"pose":{"rotation":{"radians":0.0},"translation":{"x":2.6037676732818262,"y":4.445378345302146}},"velocity":1.2089803641802959,"acceleration":-2.9999999999999827,"curvature":0,"holonomicRotation":180.0,"angularVelocity":0.0,"holonomicAngularVelocity":0.0},{"time":0.8243241115591284,"pose":{"rotation":{"radians":0.0},"translation":{"x":2.6116559447664365,"y":4.445378345302146}},"velocity":1.1892450933537038,"acceleration":-2.999999999999983,"curvature":0,"holonomicRotation":180.0,"angularVelocity":0.0,"holonomicAngularVelocity":0.0},{"time":0.831136443914146,"pose":{"rotation":{"radians":0.0},"translation":{"x":2.619687865785763,"y":4.445378345302146}},"velocity":1.1688080962886511,"acceleration":-3.0,"curvature":0,"holonomicRotation":180.0,"angularVelocity":0.0,"holonomicAngularVelocity":0.0},{"time":0.8381964328387761,"pose":{"rotation":{"radians":0.0},"translation":{"x":2.627864872835155,"y":4.445378345302146}},"velocity":1.1476281295147608,"acceleration":-3.0,"curvature":0,"holonomicRotation":180.0,"angularVelocity":0.0,"holonomicAngularVelocity":0.0},{"time":0.8455193335865994,"pose":{"rotation":{"radians":0.0},"translation":{"x":2.636188402409958,"y":4.445378345302146}},"velocity":1.125659427271291,"acceleration":-3.0,"curvature":0,"holonomicRotation":180.0,"angularVelocity":0.0,"holonomicAngularVelocity":0.0},{"time":0.8531221598400683,"pose":{"rotation":{"radians":0.0},"translation":{"x":2.6446598910055203,"y":4.445378345302146}},"velocity":1.1028509485108842,"acceleration":-2.9999999999999853,"curvature":0,"holonomicRotation":180.0,"angularVelocity":0.0,"holonomicAngularVelocity":0.0},{"time":0.8610239914869451,"pose":{"rotation":{"radians":0.0},"translation":{"x":2.6532807751171883,"y":4.445378345302146}},"velocity":1.079145453570254,"acceleration":-2.999999999999986,"curvature":0,"holonomicRotation":180.0,"angularVelocity":0.0,"holonomicAngularVelocity":0.0},{"time":0.8692463557710132,"pose":{"rotation":{"radians":0.0},"translation":{"x":2.662052491240309,"y":4.445378345302146}},"velocity":1.0544783607180497,"acceleration":-3.0000000000000133,"curvature":0,"holonomicRotation":180.0,"angularVelocity":0.0,"holonomicAngularVelocity":0.0},{"time":0.8778137044833254,"pose":{"rotation":{"radians":0.0},"translation":{"x":2.6709764758702303,"y":4.445378345302146}},"velocity":1.0287763145811128,"acceleration":-3.000000000000013,"curvature":0,"holonomicRotation":180.0,"angularVelocity":0.0,"holonomicAngularVelocity":0.0},{"time":0.886754018648581,"pose":{"rotation":{"radians":0.0},"translation":{"x":2.680054165502299,"y":4.445378345302146}},"velocity":1.001955372085346,"acceleration":-2.9999999999999876,"curvature":0,"holonomicRotation":180.0,"angularVelocity":0.0,"holonomicAngularVelocity":0.0},{"time":0.8960995851378171,"pose":{"rotation":{"radians":0.0},"translation":{"x":2.689286996631863,"y":4.445378345302146}},"velocity":0.9739186726176378,"acceleration":-3.000000000000024,"curvature":0,"holonomicRotation":180.0,"angularVelocity":0.0,"holonomicAngularVelocity":0.0},{"time":0.9058880092224195,"pose":{"rotation":{"radians":0.0},"translation":{"x":2.6986764057542674,"y":4.445378345302146}},"velocity":0.9445534003638304,"acceleration":-3.0,"curvature":0,"holonomicRotation":180.0,"angularVelocity":0.0,"holonomicAngularVelocity":0.0},{"time":0.9161635573719645,"pose":{"rotation":{"radians":0.0},"translation":{"x":2.708223829364862,"y":4.445378345302146}},"velocity":0.9137267559151954,"acceleration":-3.0,"curvature":0,"holonomicRotation":180.0,"angularVelocity":0.0,"holonomicAngularVelocity":0.0},{"time":0.9269789727517951,"pose":{"rotation":{"radians":0.0},"translation":{"x":2.7179307039589924,"y":4.445378345302146}},"velocity":0.8812805097757038,"acceleration":-2.99999999999999,"curvature":0,"holonomicRotation":180.0,"angularVelocity":0.0,"holonomicAngularVelocity":0.0},{"time":0.9383979848806023,"pose":{"rotation":{"radians":0.0},"translation":{"x":2.727798466032006,"y":4.445378345302146}},"velocity":0.8470234733892821,"acceleration":-3.0,"curvature":0,"holonomicRotation":180.0,"angularVelocity":0.0,"holonomicAngularVelocity":0.0},{"time":0.9504988693010379,"pose":{"rotation":{"radians":0.0},"translation":{"x":2.7378285520792502,"y":4.445378345302146}},"velocity":0.8107208201279755,"acceleration":-2.9999999999999907,"curvature":0,"holonomicRotation":180.0,"angularVelocity":0.0,"holonomicAngularVelocity":0.0},{"time":0.9633796515436154,"pose":{"rotation":{"radians":0.0},"translation":{"x":2.7480223985960714,"y":4.445378345302146}},"velocity":0.7720784734002432,"acceleration":-2.9999999999999916,"curvature":0,"holonomicRotation":180.0,"angularVelocity":0.0,"holonomicAngularVelocity":0.0},{"time":0.9771659941392266,"pose":{"rotation":{"radians":0.0},"translation":{"x":2.7583814420778183,"y":4.445378345302146}},"velocity":0.7307194456134096,"acceleration":-3.0,"curvature":0,"holonomicRotation":180.0,"angularVelocity":0.0,"holonomicAngularVelocity":0.0},{"time":0.9920236846789467,"pose":{"rotation":{"radians":0.0},"translation":{"x":2.768907119019837,"y":4.445378345302146}},"velocity":0.686146373994249,"acceleration":-3.0,"curvature":0,"holonomicRotation":180.0,"angularVelocity":0.0,"holonomicAngularVelocity":0.0},{"time":1.008179513093123,"pose":{"rotation":{"radians":0.0},"translation":{"x":2.779600865917475,"y":4.445378345302146}},"velocity":0.6376788887517205,"acceleration":-2.9999999999999796,"curvature":0,"holonomicRotation":180.0,"angularVelocity":0.0,"holonomicAngularVelocity":0.0},{"time":1.0259586836217691,"pose":{"rotation":{"radians":0.0},"translation":{"x":2.7904641192660793,"y":4.445378345302146}},"velocity":0.5843413771657822,"acceleration":-3.000000000000006,"curvature":0,"holonomicRotation":180.0,"angularVelocity":0.0,"holonomicAngularVelocity":0.0},{"time":1.0458583365075151,"pose":{"rotation":{"radians":0.0},"translation":{"x":2.8014983155609974,"y":4.445378345302146}},"velocity":0.5246424185085441,"acceleration":-3.0,"curvature":0,"holonomicRotation":180.0,"angularVelocity":0.0,"holonomicAngularVelocity":0.0},{"time":1.0687120205065193,"pose":{"rotation":{"radians":0.0},"translation":{"x":2.8127048912975754,"y":4.445378345302146}},"velocity":0.4560813665115318,"acceleration":-2.999999999999998,"curvature":0,"holonomicRotation":180.0,"angularVelocity":0.0,"holonomicAngularVelocity":0.0},{"time":1.0961385082763306,"pose":{"rotation":{"radians":0.0},"translation":{"x":2.8240852829711613,"y":4.445378345302146}},"velocity":0.3738019032020978,"acceleration":-2.999999999999996,"curvature":0,"holonomicRotation":180.0,"angularVelocity":0.0,"holonomicAngularVelocity":0.0},{"time":1.1322995850358792,"pose":{"rotation":{"radians":0.0},"translation":{"x":2.835640927077103,"y":4.445378345302146}},"velocity":0.2653186729234521,"acceleration":-2.9999999999999956,"curvature":0,"holonomicRotation":180.0,"angularVelocity":0.0,"holonomicAngularVelocity":0.0},{"time":1.22073914267703,"pose":{"rotation":{"radians":0.0},"translation":{"x":2.8473732601107464,"y":4.445378345302146}},"velocity":0,"acceleration":-2.9999999999999987,"curvature":0,"holonomicRotation":180.0,"angularVelocity":0.0,"holonomicAngularVelocity":0.0}]